[
 {
   "university name": "University of West London",
   "unversity website": "",
   "country": "United Kingdom",
   "city": "London",
   "university image": "https://s3.eu-north-1.amazonaws.com/images.free-apply.com/uni/gallery/245x196/1082600134/d95c8413a80070feccef0f40c914658ebf38bc1a.jpg",
   "logo image": "https://s3.eu-north-1.amazonaws.com/images.free-apply.com/uni/logo/lg/1082600134/1e0adb297313b60d42cfe2016c27b9421484d762.jpg",
   "year founded": 1860,
   "tuitition fee": 12498,
   "wikipedia link": "https://en.wikipedia.org/wiki/University_of_West_London",
   "facebook link": "",
   "twitter link": "",
   "linkedin link": "",
   "linkedin followers": "",
   "description": "",
   "facebook likes": "",
   "facebook followers": "",
   "facebook checkins": "",
   "twitter followers": "",
   "twitter following": "",
   "wiki academic affiliations": "",
   "wiki academic staff": "",
   "wiki address": "",
   "wiki administrative staff": "",
   "wiki budget": "",
   "wiki campus": "",
   "wiki endowment": "",
   "wiki founder": "",
   "wiki language": "",
   "wiki location": "",
   "wiki postgraduates": "",
   "wiki students": "",
   "wiki type": "",
   "wiki undergraduate": ""
 },
 {
   "university name": "University of Warwick",
   "unversity website": "",
   "country": "United Kingdom",
   "city": "Coventry",
   "university image": "https://s3.eu-north-1.amazonaws.com/images.free-apply.com/uni/gallery/245x196/1082600133/4e55603e0cc22e7d20bdc64d7bb8df109785f9f9.jpg",
   "logo image": "https://s3.eu-north-1.amazonaws.com/images.free-apply.com/uni/logo/lg/1082600133/6fc10142dc7f6127f94a4c4ed72aaaf78384e473.jpg",
   "year founded": 1965,
   "tuitition fee": 5263,
   "wikipedia link": "https://en.wikipedia.org/wiki/University_of_Warwick",
   "facebook link": "",
   "twitter link": "",
   "linkedin link": "",
   "linkedin followers": "",
   "description": "",
   "facebook likes": "",
   "facebook followers": "",
   "facebook checkins": "",
   "twitter followers": "",
   "twitter following": "",
   "wiki academic affiliations": "",
   "wiki academic staff": "",
   "wiki address": "",
   "wiki administrative staff": "",
   "wiki budget": "",
   "wiki campus": "",
   "wiki endowment": "",
   "wiki founder": "",
   "wiki language": "",
   "wiki location": "",
   "wiki postgraduates": "",
   "wiki students": "",
   "wiki type": "",
   "wiki undergraduate": ""
 },
 {
   "university name": "The Parkinson Building at the University of Leeds",
   "unversity website": "",
   "country": "United Kingdom",
   "city": "Leeds",
   "university image": "https://s3.eu-north-1.amazonaws.com/images.free-apply.com/uni/gallery/245x196/1082600120/e1b74f0206b6f23f047b465e6d8d38c7e095c049.jpg",
   "logo image": "https://s3.eu-north-1.amazonaws.com/images.free-apply.com/uni/logo/lg/1082600120/d2cbe66f7315c0e329d7bd834b2c2ad3cd65a20f.jpg",
   "year founded": 1951,
   "tuitition fee": 5592,
   "wikipedia link": "https://en.wikipedia.org/wiki/Parkinson_Building",
   "facebook link": "",
   "twitter link": "",
   "linkedin link": "",
   "linkedin followers": "",
   "description": "",
   "facebook likes": "",
   "facebook followers": "",
   "facebook checkins": "",
   "twitter followers": "",
   "twitter following": "",
   "wiki academic affiliations": "",
   "wiki academic staff": "",
   "wiki address": "",
   "wiki administrative staff": "",
   "wiki budget": "",
   "wiki campus": "",
   "wiki endowment": "",
   "wiki founder": "",
   "wiki language": "",
   "wiki location": "",
   "wiki postgraduates": "",
   "wiki students": "",
   "wiki type": "",
   "wiki undergraduate": ""
 },
 {
   "university name": "Heriot-Watt University",
   "unversity website": "",
   "country": "United Kingdom",
   "city": "Edinburgh",
   "university image": "https://s3.eu-north-1.amazonaws.com/images.free-apply.com/uni/gallery/245x196/1082600007/1a66c64183d7592d43cd3188870081121e8cbf0d.jpg",
   "logo image": "https://s3.eu-north-1.amazonaws.com/images.free-apply.com/uni/logo/lg/1082600007/0010ed44ce367decc6874b9768b8157a92b5474c.jpg",
   "year founded": 1821,
   "tuitition fee": 11089,
   "wikipedia link": "https://en.wikipedia.org/wiki/Heriot-Watt_University",
   "facebook link": "",
   "twitter link": "",
   "linkedin link": "",
   "linkedin followers": "",
   "description": "",
   "facebook likes": "",
   "facebook followers": "",
   "facebook checkins": "",
   "twitter followers": "",
   "twitter following": "",
   "wiki academic affiliations": "",
   "wiki academic staff": "",
   "wiki address": "",
   "wiki administrative staff": "",
   "wiki budget": "",
   "wiki campus": "",
   "wiki endowment": "",
   "wiki founder": "",
   "wiki language": "",
   "wiki location": "",
   "wiki postgraduates": "",
   "wiki students": "",
   "wiki type": "",
   "wiki undergraduate": ""
 },
 {
   "university name": "University of Sunderland",
   "unversity website": "",
   "country": "United Kingdom",
   "city": "Sunderland",
   "university image": "https://s3.eu-north-1.amazonaws.com/images.free-apply.com/uni/gallery/245x196/1082600095/35db39b811c8ba3711b1de750e4277db875148e2.jpg",
   "logo image": "https://s3.eu-north-1.amazonaws.com/images.free-apply.com/uni/logo/lg/1082600095/0dc9679004e6b7cd200a7011f9f06b8202d1a227.jpg",
   "year founded": 1901,
   "tuitition fee": 5658,
   "wikipedia link": "https://en.wikipedia.org/wiki/University_of_Sunderland",
   "facebook link": "",
   "twitter link": "",
   "linkedin link": "",
   "linkedin followers": "",
   "description": "",
   "facebook likes": "",
   "facebook followers": "",
   "facebook checkins": "",
   "twitter followers": "",
   "twitter following": "",
   "wiki academic affiliations": "",
   "wiki academic staff": "",
   "wiki address": "",
   "wiki administrative staff": "",
   "wiki budget": "",
   "wiki campus": "",
   "wiki endowment": "",
   "wiki founder": "",
   "wiki language": "",
   "wiki location": "",
   "wiki postgraduates": "",
   "wiki students": "",
   "wiki type": "",
   "wiki undergraduate": ""
 },
 {
   "university name": "Brighton and Sussex Medical School",
   "unversity website": "",
   "country": "United Kingdom",
   "city": "Brighton",
   "university image": "https://s3.eu-north-1.amazonaws.com/images.free-apply.com/uni/gallery/245x196/1082600078/767b5b16468cd8243994c22ca5377e93bb371f7b.jpg",
   "logo image": "https://s3.eu-north-1.amazonaws.com/images.free-apply.com/uni/logo/lg/1082600078/ff2c36d300293c27e24ca3d057ef79ad1ec2f07a.jpg",
   "year founded": 2002,
   "tuitition fee": 12154,
   "wikipedia link": "https://en.wikipedia.org/wiki/Brighton_and_Sussex_Medical_School",
   "facebook link": "",
   "twitter link": "",
   "linkedin link": "",
   "linkedin followers": "",
   "description": "",
   "facebook likes": "",
   "facebook followers": "",
   "facebook checkins": "",
   "twitter followers": "",
   "twitter following": "",
   "wiki academic affiliations": "",
   "wiki academic staff": "",
   "wiki address": "",
   "wiki administrative staff": "",
   "wiki budget": "",
   "wiki campus": "",
   "wiki endowment": "",
   "wiki founder": "",
   "wiki language": "",
   "wiki location": "",
   "wiki postgraduates": "",
   "wiki students": "",
   "wiki type": "",
   "wiki undergraduate": ""
 },
 {
   "university name": "Plymouth College of Art and Design",
   "unversity website": "",
   "country": "United Kingdom",
   "city": "Plymouth",
   "university image": "https://s3.eu-north-1.amazonaws.com/images.free-apply.com/uni/gallery/245x196/1082600265/d4c206cba04a1af74579561ef299a0af1c4a3238.jpg",
   "logo image": "https://s3.eu-north-1.amazonaws.com/images.free-apply.com/uni/logo/lg/1082600265/85b9b30d0c27593e0ea82105d0c1dcb79492f58f.jpg",
   "year founded": 1993,
   "tuitition fee": 11965,
   "wikipedia link": "https://en.wikipedia.org/wiki/Plymouth_College_of_Art",
   "facebook link": "",
   "twitter link": "",
   "linkedin link": "",
   "linkedin followers": "",
   "description": "",
   "facebook likes": "",
   "facebook followers": "",
   "facebook checkins": "",
   "twitter followers": "",
   "twitter following": "",
   "wiki academic affiliations": "",
   "wiki academic staff": "",
   "wiki address": "",
   "wiki administrative staff": "",
   "wiki budget": "",
   "wiki campus": "",
   "wiki endowment": "",
   "wiki founder": "",
   "wiki language": "",
   "wiki location": "",
   "wiki postgraduates": "",
   "wiki students": "",
   "wiki type": "",
   "wiki undergraduate": ""
 },
 {
   "university name": "Advanced Studies In England",
   "unversity website": "",
   "country": "United Kingdom",
   "city": "Bath",
   "university image": "https://s3.eu-north-1.amazonaws.com/images.free-apply.com/uni/gallery/245x196/1082600016/e5310756be6b15d4964dddf72cb3888dcccc2f7a.jpg",
   "logo image": "https://s3.eu-north-1.amazonaws.com/images.free-apply.com/uni/logo/lg/1082600016/3d5937da38b86561a64be3a63025938e6d7097b0.jpg",
   "year founded": 1987,
   "tuitition fee": 7833,
   "wikipedia link": "https://en.wikipedia.org/wiki/School_of_Advanced_Study",
   "facebook link": "",
   "twitter link": "",
   "linkedin link": "",
   "linkedin followers": "",
   "description": "",
   "facebook likes": "",
   "facebook followers": "",
   "facebook checkins": "",
   "twitter followers": "",
   "twitter following": "",
   "wiki academic affiliations": "",
   "wiki academic staff": "",
   "wiki address": "",
   "wiki administrative staff": "",
   "wiki budget": "",
   "wiki campus": "",
   "wiki endowment": "",
   "wiki founder": "",
   "wiki language": "",
   "wiki location": "",
   "wiki postgraduates": "",
   "wiki students": "",
   "wiki type": "",
   "wiki undergraduate": ""
 },
 {
   "university name": "New College of the Humanities",
   "unversity website": "",
   "country": "United Kingdom",
   "city": "London",
   "university image": "https://s3.eu-north-1.amazonaws.com/images.free-apply.com/uni/gallery/245x196/1082600238/9203d322191211e36db330a8b6fa2ebe7a477cfb.jpg",
   "logo image": "https://s3.eu-north-1.amazonaws.com/images.free-apply.com/uni/logo/lg/1082600238/071915cb5f42a87cfbc94eaff380677bd23d48b9.jpg",
   "year founded": 2010,
   "tuitition fee": 14281,
   "wikipedia link": "https://en.wikipedia.org/wiki/New_College_of_the_Humanities_at_Northeastern",
   "facebook link": "",
   "twitter link": "",
   "linkedin link": "",
   "linkedin followers": "",
   "description": "",
   "facebook likes": "",
   "facebook followers": "",
   "facebook checkins": "",
   "twitter followers": "",
   "twitter following": "",
   "wiki academic affiliations": "",
   "wiki academic staff": "",
   "wiki address": "",
   "wiki administrative staff": "",
   "wiki budget": "",
   "wiki campus": "",
   "wiki endowment": "",
   "wiki founder": "",
   "wiki language": "",
   "wiki location": "",
   "wiki postgraduates": "",
   "wiki students": "",
   "wiki type": "",
   "wiki undergraduate": ""
 },
 {
   "university name": "Manchester Metropolitan University",
   "unversity website": "",
   "country": "United Kingdom",
   "city": "Manchester",
   "university image": "https://s3.eu-north-1.amazonaws.com/images.free-apply.com/uni/gallery/245x196/1082600224/89c11242f94d859769d056949e335a6e42b8fb22.jpg",
   "logo image": "https://s3.eu-north-1.amazonaws.com/images.free-apply.com/uni/logo/lg/1082600224/cf84260c13b9debec7c2aa86995538f90270ef3c.jpg",
   "year founded": 1970,
   "tuitition fee": 16515,
   "wikipedia link": "https://en.wikipedia.org/wiki/Manchester_Metropolitan_University",
   "facebook link": "",
   "twitter link": "",
   "linkedin link": "",
   "linkedin followers": "",
   "description": "",
   "facebook likes": "",
   "facebook followers": "",
   "facebook checkins": "",
   "twitter followers": "",
   "twitter following": "",
   "wiki academic affiliations": "",
   "wiki academic staff": "",
   "wiki address": "",
   "wiki administrative staff": "",
   "wiki budget": "",
   "wiki campus": "",
   "wiki endowment": "",
   "wiki founder": "",
   "wiki language": "",
   "wiki location": "",
   "wiki postgraduates": "",
   "wiki students": "",
   "wiki type": "",
   "wiki undergraduate": ""
 },
 {
   "university name": "Glasgow School of Art",
   "unversity website": "",
   "country": "United Kingdom",
   "city": "Glasgow",
   "university image": "https://s3.eu-north-1.amazonaws.com/images.free-apply.com/uni/gallery/245x196/1082600031/3d97ddee645ff7bef7104de182e770002ac77e3e.jpg",
   "logo image": "https://s3.eu-north-1.amazonaws.com/images.free-apply.com/uni/logo/lg/1082600031/b810e6269d4077a6e66a9099e29ec77f697444e8.jpg",
   "year founded": 1845,
   "tuitition fee": 2380,
   "wikipedia link": "https://en.wikipedia.org/wiki/Glasgow_School_of_Art",
   "facebook link": "",
   "twitter link": "",
   "linkedin link": "",
   "linkedin followers": "",
   "description": "",
   "facebook likes": "",
   "facebook followers": "",
   "facebook checkins": "",
   "twitter followers": "",
   "twitter following": "",
   "wiki academic affiliations": "",
   "wiki academic staff": "",
   "wiki address": "",
   "wiki administrative staff": "",
   "wiki budget": "",
   "wiki campus": "",
   "wiki endowment": "",
   "wiki founder": "",
   "wiki language": "",
   "wiki location": "",
   "wiki postgraduates": "",
   "wiki students": "",
   "wiki type": "",
   "wiki undergraduate": ""
 },
 {
   "university name": "University of the West of England",
   "unversity website": "",
   "country": "United Kingdom",
   "city": "Bristol",
   "university image": "https://s3.eu-north-1.amazonaws.com/images.free-apply.com/uni/gallery/245x196/1082600126/99757db5f37bed658cb35196095117c669b6e32b.jpg",
   "logo image": "https://s3.eu-north-1.amazonaws.com/images.free-apply.com/uni/logo/lg/1082600126/3cffa10cc9d2d0a21d5a2f1e2b019996c003e796.jpg",
   "year founded": 1970,
   "tuitition fee": 9801,
   "wikipedia link": "https://en.wikipedia.org/wiki/University_of_the_West_of_England,_Bristol",
   "facebook link": "",
   "twitter link": "",
   "linkedin link": "",
   "linkedin followers": "",
   "description": "",
   "facebook likes": "",
   "facebook followers": "",
   "facebook checkins": "",
   "twitter followers": "",
   "twitter following": "",
   "wiki academic affiliations": "",
   "wiki academic staff": "",
   "wiki address": "",
   "wiki administrative staff": "",
   "wiki budget": "",
   "wiki campus": "",
   "wiki endowment": "",
   "wiki founder": "",
   "wiki language": "",
   "wiki location": "",
   "wiki postgraduates": "",
   "wiki students": "",
   "wiki type": "",
   "wiki undergraduate": ""
 },
 {
   "university name": "Leeds Trinity University",
   "unversity website": "",
   "country": "United Kingdom",
   "city": "Leeds",
   "university image": "https://s3.eu-north-1.amazonaws.com/images.free-apply.com/uni/gallery/245x196/1082600064/b2aae233eaf1fafca927bfe769320abe5ade6327.jpg",
   "logo image": "https://s3.eu-north-1.amazonaws.com/images.free-apply.com/uni/logo/lg/1082600064/342dbd0638e2a2cc5a034a3897356e35838d253b.jpg",
   "year founded": 1966,
   "tuitition fee": 14712,
   "wikipedia link": "https://en.wikipedia.org/wiki/Leeds_Trinity_University",
   "facebook link": "",
   "twitter link": "",
   "linkedin link": "",
   "linkedin followers": "",
   "description": "",
   "facebook likes": "",
   "facebook followers": "",
   "facebook checkins": "",
   "twitter followers": "",
   "twitter following": "",
   "wiki academic affiliations": "",
   "wiki academic staff": "",
   "wiki address": "",
   "wiki administrative staff": "",
   "wiki budget": "",
   "wiki campus": "",
   "wiki endowment": "",
   "wiki founder": "",
   "wiki language": "",
   "wiki location": "",
   "wiki postgraduates": "",
   "wiki students": "",
   "wiki type": "",
   "wiki undergraduate": ""
 },
 {
   "university name": "Royal Central School of Speech and Drama",
   "unversity website": "",
   "country": "United Kingdom",
   "city": "London",
   "university image": "https://s3.eu-north-1.amazonaws.com/images.free-apply.com/uni/gallery/245x196/1082600280/f5428809be7a5d17b69f3d0362a98758237bfee0.jpg",
   "logo image": "https://s3.eu-north-1.amazonaws.com/images.free-apply.com/uni/logo/lg/1082600280/804d2e7dc1b37f930080bbfa1c5122b7837e80ee.jpg",
   "year founded": 1906,
   "tuitition fee": 6140,
   "wikipedia link": "https://en.wikipedia.org/wiki/Royal_Central_School_of_Speech_and_Drama",
   "facebook link": "",
   "twitter link": "",
   "linkedin link": "",
   "linkedin followers": "",
   "description": "",
   "facebook likes": "",
   "facebook followers": "",
   "facebook checkins": "",
   "twitter followers": "",
   "twitter following": "",
   "wiki academic affiliations": "",
   "wiki academic staff": "",
   "wiki address": "",
   "wiki administrative staff": "",
   "wiki budget": "",
   "wiki campus": "",
   "wiki endowment": "",
   "wiki founder": "",
   "wiki language": "",
   "wiki location": "",
   "wiki postgraduates": "",
   "wiki students": "",
   "wiki type": "",
   "wiki undergraduate": ""
 },
 {
   "university name": "University of the West of Scotland, Paisley, Hamilton, Ayr and Dumfries",
   "unversity website": "",
   "country": "United Kingdom",
   "city": "Ayr",
   "university image": "https://s3.eu-north-1.amazonaws.com/images.free-apply.com/uni/gallery/245x196/1082600127/552c802895430ec3dddf6f4640958dbef88d8b9c.jpg",
   "logo image": "https://s3.eu-north-1.amazonaws.com/images.free-apply.com/uni/logo/lg/1082600127/6b4902c60952a0b77978fe0c8f05138fc23dc744.jpg",
   "year founded": 1897,
   "tuitition fee": 2986,
   "wikipedia link": "https://en.wikipedia.org/wiki/University_of_the_West_of_Scotland",
   "facebook link": "",
   "twitter link": "",
   "linkedin link": "",
   "linkedin followers": "",
   "description": "",
   "facebook likes": "",
   "facebook followers": "",
   "facebook checkins": "",
   "twitter followers": "",
   "twitter following": "",
   "wiki academic affiliations": "",
   "wiki academic staff": "",
   "wiki address": "",
   "wiki administrative staff": "",
   "wiki budget": "",
   "wiki campus": "",
   "wiki endowment": "",
   "wiki founder": "",
   "wiki language": "",
   "wiki location": "",
   "wiki postgraduates": "",
   "wiki students": "",
   "wiki type": "",
   "wiki undergraduate": ""
 },
 {
   "university name": "Leeds College of Art",
   "unversity website": "",
   "country": "United Kingdom",
   "city": "Leeds",
   "university image": "https://s3.eu-north-1.amazonaws.com/images.free-apply.com/uni/gallery/245x196/1082600061/40275425b72f53cfbcd9c62a35179d464ca1576b.jpg",
   "logo image": "https://s3.eu-north-1.amazonaws.com/images.free-apply.com/uni/logo/lg/1082600061/d92c79fe0100cc41615cee746f88d23cca26262e.jpg",
   "year founded": 1846,
   "tuitition fee": 12097,
   "wikipedia link": "https://en.wikipedia.org/wiki/Leeds_Arts_University",
   "facebook link": "",
   "twitter link": "",
   "linkedin link": "",
   "linkedin followers": "",
   "description": "",
   "facebook likes": "",
   "facebook followers": "",
   "facebook checkins": "",
   "twitter followers": "",
   "twitter following": "",
   "wiki academic affiliations": "",
   "wiki academic staff": "",
   "wiki address": "",
   "wiki administrative staff": "",
   "wiki budget": "",
   "wiki campus": "",
   "wiki endowment": "",
   "wiki founder": "",
   "wiki language": "",
   "wiki location": "",
   "wiki postgraduates": "",
   "wiki students": "",
   "wiki type": "",
   "wiki undergraduate": ""
 },
 {
   "university name": "Open University UK",
   "unversity website": "",
   "country": "United Kingdom",
   "city": "Milton Keynes",
   "university image": "https://s3.eu-north-1.amazonaws.com/images.free-apply.com/uni/gallery/245x196/1082600259/725ac6b41fa33ffac0f7b91f45300b096a48fcfa.jpg",
   "logo image": "https://s3.eu-north-1.amazonaws.com/images.free-apply.com/uni/logo/lg/1082600259/abe26eab650ba55aee19c2a5db3cf73493829665.jpg",
   "year founded": 1969,
   "tuitition fee": 3644,
   "wikipedia link": "https://en.wikipedia.org/wiki/Open_University",
   "facebook link": "",
   "twitter link": "",
   "linkedin link": "",
   "linkedin followers": "",
   "description": "",
   "facebook likes": "",
   "facebook followers": "",
   "facebook checkins": "",
   "twitter followers": "",
   "twitter following": "",
   "wiki academic affiliations": "",
   "wiki academic staff": "",
   "wiki address": "",
   "wiki administrative staff": "",
   "wiki budget": "",
   "wiki campus": "",
   "wiki endowment": "",
   "wiki founder": "",
   "wiki language": "",
   "wiki location": "",
   "wiki postgraduates": "",
   "wiki students": "",
   "wiki type": "",
   "wiki undergraduate": ""
 },
 {
   "university name": "Falmouth University (Dartington College of Arts)",
   "unversity website": "",
   "country": "United Kingdom",
   "city": "Falmouth",
   "university image": "https://s3.eu-north-1.amazonaws.com/images.free-apply.com/uni/gallery/245x196/1082600103/8dd4f58dd9fda6fa4c633457e47277580d6b48c7.jpg",
   "logo image": "https://s3.eu-north-1.amazonaws.com/images.free-apply.com/uni/logo/lg/1082600103/250721cf07a04b5cf87fe2f357aaa00f187a195b.jpg",
   "year founded": 1961,
   "tuitition fee": 8508,
   "wikipedia link": "https://en.wikipedia.org/wiki/Falmouth_University",
   "facebook link": "",
   "twitter link": "",
   "linkedin link": "",
   "linkedin followers": "",
   "description": "",
   "facebook likes": "",
   "facebook followers": "",
   "facebook checkins": "",
   "twitter followers": "",
   "twitter following": "",
   "wiki academic affiliations": "",
   "wiki academic staff": "",
   "wiki address": "",
   "wiki administrative staff": "",
   "wiki budget": "",
   "wiki campus": "",
   "wiki endowment": "",
   "wiki founder": "",
   "wiki language": "",
   "wiki location": "",
   "wiki postgraduates": "",
   "wiki students": "",
   "wiki type": "",
   "wiki undergraduate": ""
 },
 {
   "university name": "City College Brighton and Hove",
   "unversity website": "",
   "country": "United Kingdom",
   "city": "Brighton",
   "university image": "https://s3.eu-north-1.amazonaws.com/images.free-apply.com/uni/gallery/245x196/1082600144/cb33cf07e38b76a60fcd29e357934fdd4e2dadb3.jpg",
   "logo image": "https://s3.eu-north-1.amazonaws.com/images.free-apply.com/uni/logo/lg/1082600144/8c6efc16025e0eb9eda2282da6bf3e66d946a855.jpg",
   "year founded": 2001,
   "tuitition fee": 6418,
   "wikipedia link": "https://en.wikipedia.org/wiki/City_College_Brighton_%26_Hove",
   "facebook link": "",
   "twitter link": "",
   "linkedin link": "",
   "linkedin followers": "",
   "description": "",
   "facebook likes": "",
   "facebook followers": "",
   "facebook checkins": "",
   "twitter followers": "",
   "twitter following": "",
   "wiki academic affiliations": "",
   "wiki academic staff": "",
   "wiki address": "",
   "wiki administrative staff": "",
   "wiki budget": "",
   "wiki campus": "",
   "wiki endowment": "",
   "wiki founder": "",
   "wiki language": "",
   "wiki location": "",
   "wiki postgraduates": "",
   "wiki students": "",
   "wiki type": "",
   "wiki undergraduate": ""
 },
 {
   "university name": "European School of Economics London",
   "unversity website": "",
   "country": "United Kingdom",
   "city": "London",
   "university image": "https://s3.eu-north-1.amazonaws.com/images.free-apply.com/uni/gallery/245x196/1082600106/96c9452d5627844d3ed360d2002b6880b534e476.jpg",
   "logo image": "https://s3.eu-north-1.amazonaws.com/images.free-apply.com/uni/logo/lg/1082600106/2acfa79a814ad96e4f24f07419f9cae295f34df9.jpg",
   "year founded": 1994,
   "tuitition fee": 15654,
   "wikipedia link": "https://en.wikipedia.org/wiki/European_School_of_Economics",
   "facebook link": "",
   "twitter link": "",
   "linkedin link": "",
   "linkedin followers": "",
   "description": "",
   "facebook likes": "",
   "facebook followers": "",
   "facebook checkins": "",
   "twitter followers": "",
   "twitter following": "",
   "wiki academic affiliations": "",
   "wiki academic staff": "",
   "wiki address": "",
   "wiki administrative staff": "",
   "wiki budget": "",
   "wiki campus": "",
   "wiki endowment": "",
   "wiki founder": "",
   "wiki language": "",
   "wiki location": "",
   "wiki postgraduates": "",
   "wiki students": "",
   "wiki type": "",
   "wiki undergraduate": ""
 },
 {
   "university name": "University of Wales",
   "unversity website": "",
   "country": "United Kingdom",
   "city": "Wales",
   "university image": "https://s3.eu-north-1.amazonaws.com/images.free-apply.com/uni/gallery/245x196/1082600130/6001c9f0edaf9edd855dc2fa34aa54469b97eb71.jpg",
   "logo image": "https://s3.eu-north-1.amazonaws.com/images.free-apply.com/uni/logo/lg/1082600130/392d35f61233951d933cb60bd686a05dc397dfff.jpg",
   "year founded": 1893,
   "tuitition fee": 5477,
   "wikipedia link": "https://en.wikipedia.org/wiki/University_of_Wales",
   "facebook link": "",
   "twitter link": "",
   "linkedin link": "",
   "linkedin followers": "",
   "description": "",
   "facebook likes": "",
   "facebook followers": "",
   "facebook checkins": "",
   "twitter followers": "",
   "twitter following": "",
   "wiki academic affiliations": "",
   "wiki academic staff": "",
   "wiki address": "",
   "wiki administrative staff": "",
   "wiki budget": "",
   "wiki campus": "",
   "wiki endowment": "",
   "wiki founder": "",
   "wiki language": "",
   "wiki location": "",
   "wiki postgraduates": "",
   "wiki students": "",
   "wiki type": "",
   "wiki undergraduate": ""
 },
 {
   "university name": "University of Wolverhampton",
   "unversity website": "",
   "country": "United Kingdom",
   "city": "Wolverhampton",
   "university image": "https://s3.eu-north-1.amazonaws.com/images.free-apply.com/uni/gallery/245x196/1082600137/4cb80a6ef8369ec6ac98daf83da4cec446c9a035.jpg",
   "logo image": "https://s3.eu-north-1.amazonaws.com/images.free-apply.com/uni/logo/lg/1082600137/1cdf74811d907e0b22053e5979bb6704939ac037.jpg",
   "year founded": 1835,
   "tuitition fee": 9959,
   "wikipedia link": "https://en.wikipedia.org/wiki/University_of_Wolverhampton",
   "facebook link": "",
   "twitter link": "",
   "linkedin link": "",
   "linkedin followers": "",
   "description": "",
   "facebook likes": "",
   "facebook followers": "",
   "facebook checkins": "",
   "twitter followers": "",
   "twitter following": "",
   "wiki academic affiliations": "",
   "wiki academic staff": "",
   "wiki address": "",
   "wiki administrative staff": "",
   "wiki budget": "",
   "wiki campus": "",
   "wiki endowment": "",
   "wiki founder": "",
   "wiki language": "",
   "wiki location": "",
   "wiki postgraduates": "",
   "wiki students": "",
   "wiki type": "",
   "wiki undergraduate": ""
 },
 {
   "university name": "City of Glasgow College",
   "unversity website": "",
   "country": "United Kingdom",
   "city": "Glasgow",
   "university image": "https://s3.eu-north-1.amazonaws.com/images.free-apply.com/uni/gallery/245x196/1082600322/90d3422aa11b72e373c77a01b3bea882327c7411.jpg",
   "logo image": "https://s3.eu-north-1.amazonaws.com/images.free-apply.com/uni/logo/lg/1082600322/377f87e505123da11c4c85934c668ab9e3c88a28.jpg",
   "year founded": 2010,
   "tuitition fee": 2400,
   "wikipedia link": "https://en.wikipedia.org/wiki/City_of_Glasgow_College",
   "facebook link": "",
   "twitter link": "",
   "linkedin link": "",
   "linkedin followers": "",
   "description": "",
   "facebook likes": "",
   "facebook followers": "",
   "facebook checkins": "",
   "twitter followers": "",
   "twitter following": "",
   "wiki academic affiliations": "",
   "wiki academic staff": "",
   "wiki address": "",
   "wiki administrative staff": "",
   "wiki budget": "",
   "wiki campus": "",
   "wiki endowment": "",
   "wiki founder": "",
   "wiki language": "",
   "wiki location": "",
   "wiki postgraduates": "",
   "wiki students": "",
   "wiki type": "",
   "wiki undergraduate": ""
 },
 {
   "university name": "London College of Business",
   "unversity website": "",
   "country": "United Kingdom",
   "city": "Barking",
   "university image": "https://s3.eu-north-1.amazonaws.com/images.free-apply.com/uni/gallery/245x196/1082600202/f6453531440e6d19d4dba460b86f3557b2ea83a5.jpg",
   "logo image": "https://s3.eu-north-1.amazonaws.com/images.free-apply.com/uni/logo/lg/1082600202/8ee1343c7c8ff9369c3af3ca8ce372f2d6b7edc6.jpg",
   "year founded": 2005,
   "tuitition fee": 1947,
   "wikipedia link": "https://en.wikipedia.org/wiki/London_Business_School",
   "facebook link": "",
   "twitter link": "",
   "linkedin link": "",
   "linkedin followers": "",
   "description": "",
   "facebook likes": "",
   "facebook followers": "",
   "facebook checkins": "",
   "twitter followers": "",
   "twitter following": "",
   "wiki academic affiliations": "",
   "wiki academic staff": "",
   "wiki address": "",
   "wiki administrative staff": "",
   "wiki budget": "",
   "wiki campus": "",
   "wiki endowment": "",
   "wiki founder": "",
   "wiki language": "",
   "wiki location": "",
   "wiki postgraduates": "",
   "wiki students": "",
   "wiki type": "",
   "wiki undergraduate": ""
 },
 {
   "university name": "Manchester International College",
   "unversity website": "",
   "country": "United Kingdom",
   "city": "Manchester",
   "university image": "https://s3.eu-north-1.amazonaws.com/images.free-apply.com/uni/gallery/245x196/1082600223/528bb07e4ea4781eb86e3383edd4420be956883a.jpg",
   "logo image": "https://s3.eu-north-1.amazonaws.com/images.free-apply.com/uni/logo/lg/1082600223/e040f0167b7111bae15edab239ea9297cbcb41d6.jpg",
   "year founded": 2002,
   "tuitition fee": 13373,
   "wikipedia link": "https://en.wikipedia.org/wiki/University_of_Manchester",
   "facebook link": "",
   "twitter link": "",
   "linkedin link": "",
   "linkedin followers": "",
   "description": "",
   "facebook likes": "",
   "facebook followers": "",
   "facebook checkins": "",
   "twitter followers": "",
   "twitter following": "",
   "wiki academic affiliations": "",
   "wiki academic staff": "",
   "wiki address": "",
   "wiki administrative staff": "",
   "wiki budget": "",
   "wiki campus": "",
   "wiki endowment": "",
   "wiki founder": "",
   "wiki language": "",
   "wiki location": "",
   "wiki postgraduates": "",
   "wiki students": "",
   "wiki type": "",
   "wiki undergraduate": ""
 },
 {
   "university name": "University of Wisconsin-River Falls",
   "unversity website": "",
   "country": "United Kingdom",
   "city": "Dalkeith",
   "university image": "https://s3.eu-north-1.amazonaws.com/images.free-apply.com/uni/gallery/245x196/1082600195/2fcb4571853cd912ca2ae85a0fcc586e29d85653.jpg",
   "logo image": "https://s3.eu-north-1.amazonaws.com/images.free-apply.com/uni/logo/lg/1082600195/bf13ad23e942ca384fcfef67013d2c59fed719dd.jpg",
   "year founded": 1986,
   "tuitition fee": 8,
   "wikipedia link": "https://en.wikipedia.org/wiki/University_of_Wisconsin%E2%80%93River_Falls",
   "facebook link": "",
   "twitter link": "",
   "linkedin link": "",
   "linkedin followers": "",
   "description": "",
   "facebook likes": "",
   "facebook followers": "",
   "facebook checkins": "",
   "twitter followers": "",
   "twitter following": "",
   "wiki academic affiliations": "",
   "wiki academic staff": "",
   "wiki address": "",
   "wiki administrative staff": "",
   "wiki budget": "",
   "wiki campus": "",
   "wiki endowment": "",
   "wiki founder": "",
   "wiki language": "",
   "wiki location": "",
   "wiki postgraduates": "",
   "wiki students": "",
   "wiki type": "",
   "wiki undergraduate": ""
 },
 {
   "university name": "Conservatoire for Dance and Drama",
   "unversity website": "",
   "country": "United Kingdom",
   "city": "London",
   "university image": "https://s3.eu-north-1.amazonaws.com/images.free-apply.com/uni/gallery/245x196/1082600150/f01acafa344177815cd4b53a8af923e9d496a9c3.jpg",
   "logo image": "https://s3.eu-north-1.amazonaws.com/images.free-apply.com/uni/logo/lg/1082600150/5a6218adfdb505a0b3c568445b4bef608ebf1ffb.jpg",
   "year founded": 2001,
   "tuitition fee": 12176,
   "wikipedia link": "https://en.wikipedia.org/wiki/Conservatoire_for_Dance_and_Drama",
   "facebook link": "",
   "twitter link": "",
   "linkedin link": "",
   "linkedin followers": "",
   "description": "",
   "facebook likes": "",
   "facebook followers": "",
   "facebook checkins": "",
   "twitter followers": "",
   "twitter following": "",
   "wiki academic affiliations": "",
   "wiki academic staff": "",
   "wiki address": "",
   "wiki administrative staff": "",
   "wiki budget": "",
   "wiki campus": "",
   "wiki endowment": "",
   "wiki founder": "",
   "wiki language": "",
   "wiki location": "",
   "wiki postgraduates": "",
   "wiki students": "",
   "wiki type": "",
   "wiki undergraduate": ""
 },
 {
   "university name": "British College of Osteopathic Medicine",
   "unversity website": "",
   "country": "United Kingdom",
   "city": "London",
   "university image": "https://s3.eu-north-1.amazonaws.com/images.free-apply.com/uni/gallery/245x196/1082600082/a2bd0224d0936ba2faa8f30bd5d717269537670d.jpg",
   "logo image": "https://s3.eu-north-1.amazonaws.com/images.free-apply.com/uni/logo/lg/1082600082/3dbfa7c094a502ef5bf170a116d856fb56d5d01c.jpg",
   "year founded": 1936,
   "tuitition fee": 7894,
   "wikipedia link": "https://en.wikipedia.org/wiki/British_College_of_Osteopathic_Medicine",
   "facebook link": "",
   "twitter link": "",
   "linkedin link": "",
   "linkedin followers": "",
   "description": "",
   "facebook likes": "",
   "facebook followers": "",
   "facebook checkins": "",
   "twitter followers": "",
   "twitter following": "",
   "wiki academic affiliations": "",
   "wiki academic staff": "",
   "wiki address": "",
   "wiki administrative staff": "",
   "wiki budget": "",
   "wiki campus": "",
   "wiki endowment": "",
   "wiki founder": "",
   "wiki language": "",
   "wiki location": "",
   "wiki postgraduates": "",
   "wiki students": "",
   "wiki type": "",
   "wiki undergraduate": ""
 },
 {
   "university name": "American University for Leaders",
   "unversity website": "",
   "country": "United Kingdom",
   "city": "London",
   "university image": "https://s3.eu-north-1.amazonaws.com/images.free-apply.com/uni/gallery/245x196/1082600021/7e6a4865af16b39420572ff968f29624e2af1228.jpg",
   "logo image": "https://s3.eu-north-1.amazonaws.com/images.free-apply.com/uni/logo/lg/1082600021/e073e6ced5441ab0f9468bf9bb59c967495c18c1.jpg",
   "year founded": 1986,
   "tuitition fee": 5875,
   "wikipedia link": "https://en.wikipedia.org/wiki/American_University",
   "facebook link": "",
   "twitter link": "",
   "linkedin link": "",
   "linkedin followers": "",
   "description": "",
   "facebook likes": "",
   "facebook followers": "",
   "facebook checkins": "",
   "twitter followers": "",
   "twitter following": "",
   "wiki academic affiliations": "",
   "wiki academic staff": "",
   "wiki address": "",
   "wiki administrative staff": "",
   "wiki budget": "",
   "wiki campus": "",
   "wiki endowment": "",
   "wiki founder": "",
   "wiki language": "",
   "wiki location": "",
   "wiki postgraduates": "",
   "wiki students": "",
   "wiki type": "",
   "wiki undergraduate": ""
 },
 {
   "university name": "Blackburn College",
   "unversity website": "",
   "country": "United Kingdom",
   "city": "Blackburn",
   "university image": "https://s3.eu-north-1.amazonaws.com/images.free-apply.com/uni/gallery/245x196/1082600057/9efaf5d106edac7b4044a8f137b767747d707734.jpg",
   "logo image": "https://s3.eu-north-1.amazonaws.com/images.free-apply.com/uni/logo/lg/1082600057/8ca5173c007bcee9b504f5c6300a49f7b390a724.jpg",
   "year founded": 1888,
   "tuitition fee": 8823,
   "wikipedia link": "https://en.wikipedia.org/wiki/Blackburn_College_(Illinois)",
   "facebook link": "",
   "twitter link": "",
   "linkedin link": "",
   "linkedin followers": "",
   "description": "",
   "facebook likes": "",
   "facebook followers": "",
   "facebook checkins": "",
   "twitter followers": "",
   "twitter following": "",
   "wiki academic affiliations": "",
   "wiki academic staff": "",
   "wiki address": "",
   "wiki administrative staff": "",
   "wiki budget": "",
   "wiki campus": "",
   "wiki endowment": "",
   "wiki founder": "",
   "wiki language": "",
   "wiki location": "",
   "wiki postgraduates": "",
   "wiki students": "",
   "wiki type": "",
   "wiki undergraduate": ""
 },
 {
   "university name": "Newman University",
   "unversity website": "",
   "country": "United Kingdom",
   "city": "Birmingham",
   "university image": "https://s3.eu-north-1.amazonaws.com/images.free-apply.com/uni/gallery/245x196/1082600244/cfe9210a65952743e5d2a8afae29536d7d0cfd4d.jpg",
   "logo image": "https://s3.eu-north-1.amazonaws.com/images.free-apply.com/uni/logo/lg/1082600244/fd109fd88d7eaad5a25e586b43853d0e980b9c78.jpg",
   "year founded": 1968,
   "tuitition fee": 12009,
   "wikipedia link": "https://en.wikipedia.org/wiki/Newman_University,_Wichita",
   "facebook link": "",
   "twitter link": "",
   "linkedin link": "",
   "linkedin followers": "",
   "description": "",
   "facebook likes": "",
   "facebook followers": "",
   "facebook checkins": "",
   "twitter followers": "",
   "twitter following": "",
   "wiki academic affiliations": "",
   "wiki academic staff": "",
   "wiki address": "",
   "wiki administrative staff": "",
   "wiki budget": "",
   "wiki campus": "",
   "wiki endowment": "",
   "wiki founder": "",
   "wiki language": "",
   "wiki location": "",
   "wiki postgraduates": "",
   "wiki students": "",
   "wiki type": "",
   "wiki undergraduate": ""
 },
 {
   "university name": "NYU in London",
   "unversity website": "",
   "country": "United Kingdom",
   "city": "London",
   "university image": "https://s3.eu-north-1.amazonaws.com/images.free-apply.com/uni/gallery/245x196/1082600254/fca374e8d113157fad4d12ab7519dbcbe1128ee6.jpg",
   "logo image": "https://s3.eu-north-1.amazonaws.com/images.free-apply.com/uni/logo/lg/1082600254/e271b6675b22d3cdb6ed5d4a1366ab24caf58c53.jpg",
   "year founded": 1958,
   "tuitition fee": 48855,
   "wikipedia link": "https://en.wikipedia.org/wiki/NYU_London",
   "facebook link": "",
   "twitter link": "",
   "linkedin link": "",
   "linkedin followers": "",
   "description": "",
   "facebook likes": "",
   "facebook followers": "",
   "facebook checkins": "",
   "twitter followers": "",
   "twitter following": "",
   "wiki academic affiliations": "",
   "wiki academic staff": "",
   "wiki address": "",
   "wiki administrative staff": "",
   "wiki budget": "",
   "wiki campus": "",
   "wiki endowment": "",
   "wiki founder": "",
   "wiki language": "",
   "wiki location": "",
   "wiki postgraduates": "",
   "wiki students": "",
   "wiki type": "",
   "wiki undergraduate": ""
 },
 {
   "university name": "Southampton Solent University",
   "unversity website": "",
   "country": "United Kingdom",
   "city": "Southampton",
   "university image": "https://s3.eu-north-1.amazonaws.com/images.free-apply.com/uni/gallery/245x196/1082600309/9b0bf2441d88c98be406e0445988fdde05d52215.jpg",
   "logo image": "https://s3.eu-north-1.amazonaws.com/images.free-apply.com/uni/logo/lg/1082600309/a621f72de39b928e8f85644fb9173d0f919f7d5c.jpg",
   "year founded": 2004,
   "tuitition fee": 10017,
   "wikipedia link": "https://en.wikipedia.org/wiki/Solent_University",
   "facebook link": "",
   "twitter link": "",
   "linkedin link": "",
   "linkedin followers": "",
   "description": "",
   "facebook likes": "",
   "facebook followers": "",
   "facebook checkins": "",
   "twitter followers": "",
   "twitter following": "",
   "wiki academic affiliations": "",
   "wiki academic staff": "",
   "wiki address": "",
   "wiki administrative staff": "",
   "wiki budget": "",
   "wiki campus": "",
   "wiki endowment": "",
   "wiki founder": "",
   "wiki language": "",
   "wiki location": "",
   "wiki postgraduates": "",
   "wiki students": "",
   "wiki type": "",
   "wiki undergraduate": ""
 },
 {
   "university name": "Hartpury College",
   "unversity website": "",
   "country": "United Kingdom",
   "city": "Gloucester",
   "university image": "https://s3.eu-north-1.amazonaws.com/images.free-apply.com/uni/gallery/245x196/1082600005/e83c741c3b245d256bc0c589d9d96d1f862f4916.jpg",
   "logo image": "https://s3.eu-north-1.amazonaws.com/images.free-apply.com/uni/logo/lg/1082600005/9cb1463f33503d8ef85883324fa5ccdf5629cfa2.jpg",
   "year founded": 1947,
   "tuitition fee": 11305,
   "wikipedia link": "https://en.wikipedia.org/wiki/Hartpury_College",
   "facebook link": "",
   "twitter link": "",
   "linkedin link": "",
   "linkedin followers": "",
   "description": "",
   "facebook likes": "",
   "facebook followers": "",
   "facebook checkins": "",
   "twitter followers": "",
   "twitter following": "",
   "wiki academic affiliations": "",
   "wiki academic staff": "",
   "wiki address": "",
   "wiki administrative staff": "",
   "wiki budget": "",
   "wiki campus": "",
   "wiki endowment": "",
   "wiki founder": "",
   "wiki language": "",
   "wiki location": "",
   "wiki postgraduates": "",
   "wiki students": "",
   "wiki type": "",
   "wiki undergraduate": ""
 },
 {
   "university name": "Hull College",
   "unversity website": "",
   "country": "United Kingdom",
   "city": "Kingston upon Hull",
   "university image": "https://s3.eu-north-1.amazonaws.com/images.free-apply.com/uni/gallery/245x196/1082600025/758a0f2d63bc4656a0f49d22d1590720fc954ab3.jpg",
   "logo image": "https://s3.eu-north-1.amazonaws.com/images.free-apply.com/uni/logo/lg/1082600025/9b68c7e519c0e01f1dfc19edb6f34987efde414f.jpg",
   "year founded": 1913,
   "tuitition fee": 7846,
   "wikipedia link": "https://en.wikipedia.org/wiki/Hull_College",
   "facebook link": "",
   "twitter link": "",
   "linkedin link": "",
   "linkedin followers": "",
   "description": "",
   "facebook likes": "",
   "facebook followers": "",
   "facebook checkins": "",
   "twitter followers": "",
   "twitter following": "",
   "wiki academic affiliations": "",
   "wiki academic staff": "",
   "wiki address": "",
   "wiki administrative staff": "",
   "wiki budget": "",
   "wiki campus": "",
   "wiki endowment": "",
   "wiki founder": "",
   "wiki language": "",
   "wiki location": "",
   "wiki postgraduates": "",
   "wiki students": "",
   "wiki type": "",
   "wiki undergraduate": ""
 },
 {
   "university name": "Blackpool and The Fylde College",
   "unversity website": "",
   "country": "United Kingdom",
   "city": "Blackpool",
   "university image": "https://s3.eu-north-1.amazonaws.com/images.free-apply.com/uni/gallery/245x196/1082600058/17934fb8a999b42a5154f7f97b6c01586bd40e42.jpg",
   "logo image": "https://s3.eu-north-1.amazonaws.com/images.free-apply.com/uni/logo/lg/1082600058/2ab2d4ecf2fedb48b9ab7cf957eaf9f7baf50955.jpg",
   "year founded": 1892,
   "tuitition fee": 9808,
   "wikipedia link": "https://en.wikipedia.org/wiki/Blackpool_and_The_Fylde_College",
   "facebook link": "",
   "twitter link": "",
   "linkedin link": "",
   "linkedin followers": "",
   "description": "",
   "facebook likes": "",
   "facebook followers": "",
   "facebook checkins": "",
   "twitter followers": "",
   "twitter following": "",
   "wiki academic affiliations": "",
   "wiki academic staff": "",
   "wiki address": "",
   "wiki administrative staff": "",
   "wiki budget": "",
   "wiki campus": "",
   "wiki endowment": "",
   "wiki founder": "",
   "wiki language": "",
   "wiki location": "",
   "wiki postgraduates": "",
   "wiki students": "",
   "wiki type": "",
   "wiki undergraduate": ""
 },
 {
   "university name": "All Nations Christian College",
   "unversity website": "",
   "country": "United Kingdom",
   "city": "Ware",
   "university image": "https://s3.eu-north-1.amazonaws.com/images.free-apply.com/uni/gallery/245x196/1082600020/70ce3c8ee678125da19856af977831f18ee32d28.jpg",
   "logo image": "https://s3.eu-north-1.amazonaws.com/images.free-apply.com/uni/logo/lg/1082600020/762dc79d2aa0fe20c0ddd006d1ba02a45dc977f4.jpg",
   "year founded": 1971,
   "tuitition fee": 14688,
   "wikipedia link": "https://en.wikipedia.org/wiki/All_Nations_Christian_College",
   "facebook link": "",
   "twitter link": "",
   "linkedin link": "",
   "linkedin followers": "",
   "description": "",
   "facebook likes": "",
   "facebook followers": "",
   "facebook checkins": "",
   "twitter followers": "",
   "twitter following": "",
   "wiki academic affiliations": "",
   "wiki academic staff": "",
   "wiki address": "",
   "wiki administrative staff": "",
   "wiki budget": "",
   "wiki campus": "",
   "wiki endowment": "",
   "wiki founder": "",
   "wiki language": "",
   "wiki location": "",
   "wiki postgraduates": "",
   "wiki students": "",
   "wiki type": "",
   "wiki undergraduate": ""
 }
]